dog_cli/__init__.py
dog_cli/main.py
dog_core/__init__.py
dog_core/export.py
dog_core/finder.py
dog_core/formatter.py
dog_core/getter.py
dog_core/graph.py
dog_core/indexer.py
dog_core/linter.py
dog_core/models.py
dog_core/parser.py
dog_core/patcher.py
dog_core/refs.py
dog_core/search.py
dog_core/server.py
dog_cli-2025.12.7.post2.dist-info/METADATA
dog_cli-2025.12.7.post2.dist-info/WHEEL
dog_cli-2025.12.7.post2.dist-info/entry_points.txt
dog_cli-2025.12.7.post2.dist-info/licenses/LICENSE
dog_cli-2025.12.7.post2.dist-info/RECORD
