Metadata-Version: 2.4
Name: dog-cli
Version: 2025.12.7.post2
Summary: Documentation Oriented Grammar (DOG) CLI Tool
Author-email: Qian Zhang <contact@qzsh.email>
License: MIT License
License-File: LICENSE
Keywords: ai,cli,documentation,dog,llm,markdown,nlp,tool
Classifier: Development Status :: 4 - Beta
Classifier: License :: Other/Proprietary License
Classifier: Operating System :: OS Independent
Classifier: Programming Language :: Python :: 3
Classifier: Programming Language :: Python :: 3.13
Requires-Python: <3.14,>=3.13
Requires-Dist: fastapi>=0.115
Requires-Dist: marko>=2.2.1
Requires-Dist: pydantic>=2.12
Requires-Dist: rapidfuzz>=3.0
Requires-Dist: typer>=0.20.0
Requires-Dist: uvicorn>=0.34
Requires-Dist: watchfiles>=1.0
